ahuella/__init__.py
ahuella/aiohttp.py
ahuella/api.py
ahuella/exceptions.py
ahuella/models.py
ahuella/v1.py
ahuella/v2.py
ahuella/models/__init__.py
ahuella/models/v1.py
ahuella/models/v2.py
ahuella-0.0.2.dist-info/LICENSE
ahuella-0.0.2.dist-info/METADATA
ahuella-0.0.2.dist-info/WHEEL
ahuella-0.0.2.dist-info/top_level.txt
ahuella-0.0.2.dist-info/RECORD
