Metadata-Version: 2.1
Name: ahuella
Version: 0.0.2
Summary: module for api.hella.team
Home-page: https://github.com/tembz/ahuella
Author: tembz&tenkawaa
Author-email: tembz@vk.com
Keywords: ahuella
Classifier: Programming Language :: Python :: 3.11
Classifier: License :: OSI Approved :: MIT License
Classifier: Operating System :: OS Independent
Requires-Python: >=3.10
License-File: LICENSE
Requires-Dist: aiphttp
Requires-Dist: dacite
